{
  "resourceType": "CodeSystem",
  "status": "draft",
  "content": "complete",
  "name": "MII_CS_Onko_Fernmetastasen_Lokalisation",
  "id": "mii-cs-onko-fernmetastasen-lokalisation",
  "title": "MII CS Onko Fernmetastasen-Lokalisation",
  "description": "Lokalisation von Fernmetastasen",
  "url": "https://www.medizininformatik-initiative.de/fhir/ext/modul-onko/CodeSystem/mii-cs-onko-fernmetastasen-lokalisation",
  "concept": [
    {
      "code": "PUL",
      "display": "Lunge"
    },
    {
      "code": "OSS",
      "display": "Knochen"
    },
    {
      "code": "HEP",
      "display": "Leber"
    },
    {
      "code": "BRA",
      "display": "Hirn"
    },
    {
      "code": "LYM",
      "display": "Lymphknoten"
    },
    {
      "code": "MAR",
      "display": "Knochenmark"
    },
    {
      "code": "PLE",
      "display": "Pleura"
    },
    {
      "code": "PER",
      "display": "Peritoneum"
    },
    {
      "code": "ADR",
      "display": "Nebennieren"
    },
    {
      "code": "SKI",
      "display": "Haut"
    },
    {
      "code": "OTH",
      "display": "andere Organe"
    },
    {
      "code": "GEN",
      "display": "generalisierte Metastasierung"
    }
  ],
  "count": 12
}
