{
  "resourceType": "CodeSystem",
  "status": "draft",
  "content": "complete",
  "name": "MII_CS_Onko_Operation_Intention",
  "id": "mii-cs-onko-operation-intention",
  "title": "MII CS Onkologie Operation Intention",
  "description": "oBDS-spezifisches Codesystem für Klassifikation von Intention der OP",
  "url": "https://www.medizininformatik-initiative.de/fhir/ext/modul-onko/CodeSystem/mii-cs-operation-intention",
  "concept": [
    {
      "code": "K",
      "display": "kurativ"
    },
    {
      "code": "P",
      "display": "palliativ"
    },
    {
      "code": "D",
      "display": "diagnostisch"
    },
    {
      "code": "R",
      "display": "Revision/Komplikation"
    },
    {
      "code": "S",
      "display": "Sonstiges"
    },
    {
      "code": "X",
      "display": "fehlende Angabe"
    }
  ],
  "meta": {
    "profile": [
      "http://hl7.org/fhir/StructureDefinition/shareablecodesystem"
    ]
  },
  "experimental": false,
  "publisher": "Medizininformatik Initiative",
  "contact": [
    {
      "telecom": [
        {
          "system": "url",
          "value": "https://www.medizininformatik-initiative.de"
        }
      ]
    }
  ],
  "version": "2024.0.0-ballot",
  "caseSensitive": true,
  "valueSet": "https://www.medizininformatik-initiative.de/fhir/ext/modul-onko/ValueSet/mii-vs-onko-operation-intention",
  "count": 6
}
