{
  "resourceType": "MedicationStatement",
  "id": "mii-exa-onko-systemische-therapie",
  "meta": {
    "profile": [
      "https://www.medizininformatik-initiative.de/fhir/ext/modul-onko/StructureDefinition/mii-pr-onko-systemische-therapie"
    ]
  },
  "extension": [
    {
      "url": "http://fhir.de/onkologie/StructureDefinition/Intention",
      "valueCodeableConcept": {
        "coding": [
          {
            "code": "K",
            "system": "https://www.medizininformatik-initiative.de/fhir/ext/modul-onko/CodeSystem/mii-cs-onko-intention"
          }
        ]
      }
    },
    {
      "url": "http://fhir.de/onkologie/StructureDefinition/StellungZurOp",
      "valueCodeableConcept": {
        "coding": [
          {
            "code": "A",
            "system": "https://www.medizininformatik-initiative.de/fhir/ext/modul-onko/CodeSystem/mii-cs-onko-stellung-op"
          }
        ]
      }
    },
    {
      "url": "https://www.medizininformatik-initiative.de/fhir/ext/modul-onko/StructureDefinition/mii-ex-onko-therapie-ende-grund",
      "valueCodeableConcept": {
        "coding": [
          {
            "code": "E",
            "system": "https://www.medizininformatik-initiative.de/fhir/ext/modul-onko/CodeSystem/mii-cs-onko-therapie-ende-grund"
          }
        ]
      }
    }
  ],
  "status": "completed",
  "effectivePeriod": {
    "start": "2021-01-01"
  },
  "medicationCodeableConcept": {
    "coding": [
      {
        "code": "74470007",
        "system": "http://snomed.info/sct"
      }
    ]
  },
  "subject": {
    "reference": "Patient/PatientExample"
  }
}
