{
  "resourceType": "StructureDefinition",
  "id": "mii-pr-onko-tnm-a-symbol",
  "url": "https://www.medizininformatik-initiative.de/fhir/ext/modul-onko/StructureDefinition/mii-pr-onko-tnm-a-symbol",
  "version": "2024.0.0-ballot",
  "name": "MII_PR_Onko_TNM_a_Symbol",
  "title": "MII PR Onkologie TNM a-Symbol",
  "status": "draft",
  "publisher": "Medizininformatik Initiative",
  "contact": [
    {
      "telecom": [
        {
          "system": "url",
          "value": "https://www.medizininformatik-initiative.de"
        }
      ]
    }
  ],
  "description": "TNM-Klassifikation: TNM a-Symbol. Gibt an, ob die Klassifikation aus Anlass einer Autopsie erfolgte.",
  "fhirVersion": "4.0.1",
  "mapping": [
    {
      "identity": "oBDS",
      "name": "Mapping FHIR zu oBDS"
    }
  ],
  "kind": "resource",
  "abstract": false,
  "type": "Observation",
  "baseDefinition": "http://hl7.org/fhir/StructureDefinition/Observation",
  "derivation": "constraint",
  "differential": {
    "element": [
      {
        "id": "Observation.meta.profile",
        "path": "Observation.meta.profile",
        "mustSupport": true
      },
      {
        "id": "Observation.status",
        "path": "Observation.status",
        "mustSupport": true
      },
      {
        "id": "Observation.code",
        "path": "Observation.code",
        "patternCodeableConcept": {
          "coding": [
            {
              "code": "101660-9",
              "system": "http://loinc.org"
            }
          ]
        },
        "mustSupport": true
      },
      {
        "id": "Observation.code.coding.system",
        "path": "Observation.code.coding.system",
        "min": 1,
        "mustSupport": true
      },
      {
        "id": "Observation.code.coding.code",
        "path": "Observation.code.coding.code",
        "min": 1,
        "mustSupport": true
      },
      {
        "id": "Observation.subject",
        "path": "Observation.subject",
        "min": 1,
        "type": [
          {
            "code": "Reference",
            "targetProfile": [
              "http://hl7.org/fhir/StructureDefinition/Patient"
            ]
          }
        ],
        "mustSupport": true
      },
      {
        "id": "Observation.focus",
        "path": "Observation.focus",
        "type": [
          {
            "code": "Reference",
            "targetProfile": [
              "https://www.medizininformatik-initiative.de/fhir/ext/modul-onko/StructureDefinition/mii-pr-onko-diagnose"
            ]
          }
        ],
        "mustSupport": true
      },
      {
        "id": "Observation.encounter",
        "path": "Observation.encounter",
        "mustSupport": true
      },
      {
        "id": "Observation.effective[x]",
        "path": "Observation.effective[x]",
        "type": [
          {
            "code": "dateTime"
          }
        ],
        "constraint": [
          {
            "key": "tnm-datum",
            "severity": "error",
            "human": "TNM Datum: Ein exaktes (taggenaues) Datum ist anzugeben.",
            "expression": "$this.toString().length() >= 8",
            "source": "https://www.medizininformatik-initiative.de/fhir/ext/modul-onko/StructureDefinition/mii-pr-onko-tnm-a-symbol"
          }
        ],
        "mustSupport": true,
        "mapping": [
          {
            "identity": "oBDS",
            "map": "8.1",
            "comment": "TNM Datum"
          }
        ]
      },
      {
        "id": "Observation.value[x]",
        "path": "Observation.value[x]",
        "short": "a-Symbol",
        "definition": "Gibt an, ob die Klassifikation aus Anlass einer Autopsie erfolgte.",
        "comment": "a = Klassifikation erfolgte durch Autopsie; (leer) = Klassifikation erfolgte nicht durch Autopsie",
        "type": [
          {
            "code": "CodeableConcept"
          }
        ],
        "patternCodeableConcept": {
          "coding": [
            {
              "code": "421426001",
              "system": "http://snomed.info/sct"
            }
          ]
        },
        "mustSupport": true
      },
      {
        "id": "Observation.value[x].coding.system",
        "path": "Observation.value[x].coding.system",
        "min": 1,
        "mustSupport": true
      },
      {
        "id": "Observation.value[x].coding.code",
        "path": "Observation.value[x].coding.code",
        "min": 1,
        "mustSupport": true,
        "mapping": [
          {
            "identity": "oBDS",
            "map": "8.5",
            "comment": "TNM a-Symbol"
          }
        ]
      },
      {
        "id": "Observation.derivedFrom",
        "path": "Observation.derivedFrom",
        "max": "1",
        "type": [
          {
            "code": "Reference",
            "targetProfile": [
              "https://www.medizininformatik-initiative.de/fhir/ext/modul-onko/StructureDefinition/mii-pr-onko-verlauf"
            ]
          }
        ],
        "mustSupport": true
      }
    ]
  }
}
