{
  "resourceType": "ValueSet",
  "status": "draft",
  "name": "MII_VS_Onko_Therapie_Ende_Grund",
  "id": "mii-vs-onko-therapie-ende-grund",
  "title": "MII VS Onko Therapie Ende Grund",
  "description": "Grund für das Ende der Therapie",
  "url": "https://www.medizininformatik-initiative.de/fhir/ext/modul-onko/ValueSet/mii-vs-onko-therapie-ende-grund",
  "compose": {
    "include": [
      {
        "system": "https://www.medizininformatik-initiative.de/fhir/ext/modul-onko/CodeSystem/mii-cs-onko-therapie-ende-grund"
      }
    ]
  }
}
